cosmol/__init__.py
cosmol-0.0.1.dev1.dist-info/METADATA
cosmol-0.0.1.dev1.dist-info/WHEEL
cosmol-0.0.1.dev1.dist-info/top_level.txt
cosmol-0.0.1.dev1.dist-info/RECORD
