Metadata-Version: 2.1
Name: cosmol
Version: 0.0.1.dev1
Summary: COSMol: Comprehensive Structured Representation Learning Framework for Biomolecules
Author-email: 95028 <wjt@cosmol.org>
Requires-Python: >=3.7
